MLme/__init__.py
MLme/structued_data.py
MLme/structured_data.py
MLme-0.0.102.dist-info/METADATA
MLme-0.0.102.dist-info/RECORD
MLme-0.0.102.dist-info/WHEEL
MLme-0.0.102.dist-info/top_level.txt
